odoo/addons/sale_timesheet_purchase/README.rst
odoo/addons/sale_timesheet_purchase/__init__.py
odoo/addons/sale_timesheet_purchase/__manifest__.py
odoo/addons/sale_timesheet_purchase/controllers/__init__.py
odoo/addons/sale_timesheet_purchase/controllers/main.py
odoo/addons/sale_timesheet_purchase/i18n/fr.po
odoo/addons/sale_timesheet_purchase/i18n/sale_timesheet_purchase.pot
odoo/addons/sale_timesheet_purchase/readme/CONTRIBUTORS.rst
odoo/addons/sale_timesheet_purchase/readme/CREDITS.rst
odoo/addons/sale_timesheet_purchase/readme/DESCRIPTION.rst
odoo/addons/sale_timesheet_purchase/static/description/icon.png
odoo/addons/sale_timesheet_purchase/static/description/index.html
odoo12_addon_sale_timesheet_purchase-12.0.1.0.1.dist-info/METADATA
odoo12_addon_sale_timesheet_purchase-12.0.1.0.1.dist-info/WHEEL
odoo12_addon_sale_timesheet_purchase-12.0.1.0.1.dist-info/top_level.txt
odoo12_addon_sale_timesheet_purchase-12.0.1.0.1.dist-info/RECORD
